{"type":"Topology","objects":{"MI":{"type":"GeometryCollection","geometries":[{"type":"Polygon","properties":{"name":"Benzie","geoid":"26019"},"id":"26019","arcs":[[0,1,2,3]]},{"type":"Polygon","properties":{"name":"Wexford","geoid":"26165"},"id":"26165","arcs":[[4,5,6,7,8]]},{"type":"Polygon","properties":{"name":"Allegan","geoid":"26005"},"id":"26005","arcs":[[9,10,11,12,13,14]]},{"type":"Polygon","properties":{"name":"Montcalm","geoid":"26117"},"id":"26117","arcs":[[15,16,17,18,19,20]]},{"type":"Polygon","properties":{"name":"Lenawee","geoid":"26091"},"id":"26091","arcs":[[21,22,23,24,25]]},{"type":"Polygon","properties":{"name":"Mecosta","geoid":"26107"},"id":"26107","arcs":[[26,27,-16,28]]},{"type":"Polygon","properties":{"name":"Oceana","geoid":"26127"},"id":"26127","arcs":[[29,30,31,32]]},{"type":"Polygon","properties":{"name":"Livingston","geoid":"26093"},"id":"26093","arcs":[[33,34,35,36,37,38]]},{"type":"Polygon","properties":{"name":"Otsego","geoid":"26137"},"id":"26137","arcs":[[39,40,41,42,43]]},{"type":"Polygon","properties":{"name":"Clinton","geoid":"26037"},"id":"26037","arcs":[[44,45,46,47,48]]},{"type":"Polygon","properties":{"name":"Eaton","geoid":"26045"},"id":"26045","arcs":[[49,-48,50,51,52,53]]},{"type":"Polygon","properties":{"name":"Ionia","geoid":"26067"},"id":"26067","arcs":[[-19,-49,-50,54,55]]},{"type":"Polygon","properties":{"name":"Kalamazoo","geoid":"26077"},"id":"26077","arcs":[[-13,56,57,58,59]]},{"type":"Polygon","properties":{"name":"Lake","geoid":"26085"},"id":"26085","arcs":[[60,-8,61,62,63]]},{"type":"Polygon","properties":{"name":"Newaygo","geoid":"26123"},"id":"26123","arcs":[[-31,-63,-29,-21,64,65]]},{"type":"Polygon","properties":{"name":"Clare","geoid":"26035"},"id":"26035","arcs":[[66,67,68,69,70]]},{"type":"Polygon","properties":{"name":"Gladwin","geoid":"26051"},"id":"26051","arcs":[[71,72,73,74,75,-69]]},{"type":"Polygon","properties":{"name":"Montmorency","geoid":"26119"},"id":"26119","arcs":[[76,77,78,79,-42]]},{"type":"Polygon","properties":{"name":"Isabella","geoid":"26073"},"id":"26073","arcs":[[-70,80,81,-17,-28]]},{"type":"Polygon","properties":{"name":"Barry","geoid":"26015"},"id":"26015","arcs":[[82,-55,-54,83,-57,-12]]},{"type":"Polygon","properties":{"name":"Iosco","geoid":"26069"},"id":"26069","arcs":[[84,85,86,87]]},{"type":"Polygon","properties":{"name":"Luce","geoid":"26095"},"id":"26095","arcs":[[88,89,90,91,92]]},{"type":"Polygon","properties":{"name":"Manistee","geoid":"26101"},"id":"26101","arcs":[[-3,-9,-61,93,94]]},{"type":"Polygon","properties":{"name":"Roscommon","geoid":"26143"},"id":"26143","arcs":[[95,96,-72,-68,97]]},{"type":"Polygon","properties":{"name":"Missaukee","geoid":"26113"},"id":"26113","arcs":[[98,-98,-67,99,-6]]},{"type":"Polygon","properties":{"name":"Kalkaska","geoid":"26079"},"id":"26079","arcs":[[100,101,-99,102]]},{"type":"Polygon","properties":{"name":"Menominee","geoid":"26109"},"id":"26109","arcs":[[103,104,105,106]]},{"type":"Polygon","properties":{"name":"Muskegon","geoid":"26121"},"id":"26121","arcs":[[-32,-66,107,108,109]]},{"type":"Polygon","properties":{"name":"Monroe","geoid":"26115"},"id":"26115","arcs":[[110,111,112,-24]]},{"type":"Polygon","properties":{"name":"Macomb","geoid":"26099"},"id":"26099","arcs":[[113,114,115,116,117]]},{"type":"Polygon","properties":{"name":"Alger","geoid":"26003"},"id":"26003","arcs":[[118,-89,119,120,121]]},{"type":"Polygon","properties":{"name":"Bay","geoid":"26017"},"id":"26017","arcs":[[-75,122,123,124,125,126]]},{"type":"Polygon","properties":{"name":"Ottawa","geoid":"26139"},"id":"26139","arcs":[[-109,127,-10,128]]},{"type":"Polygon","properties":{"name":"Emmet","geoid":"26047"},"id":"26047","arcs":[[129,130,131]]},{"type":"MultiPolygon","properties":{"name":"Leelanau","geoid":"26089"},"id":"26089","arcs":[[[132]],[[133]],[[134]],[[135,-1,136]],[[137]]]},{"type":"Polygon","properties":{"name":"Jackson","geoid":"26075"},"id":"26075","arcs":[[-52,138,-38,139,-22,140,141]]},{"type":"Polygon","properties":{"name":"Cheboygan","geoid":"26031"},"id":"26031","arcs":[[-130,142,143,-77,-41,144]]},{"type":"Polygon","properties":{"name":"Gogebic","geoid":"26053"},"id":"26053","arcs":[[145,146,147]]},{"type":"Polygon","properties":{"name":"Berrien","geoid":"26021"},"id":"26021","arcs":[[148,149,150]]},{"type":"Polygon","properties":{"name":"Hillsdale","geoid":"26059"},"id":"26059","arcs":[[151,-141,-26,152,153]]},{"type":"Polygon","properties":{"name":"Houghton","geoid":"26061"},"id":"26061","arcs":[[154,155,156,157,158,159]]},{"type":"Polygon","properties":{"name":"Branch","geoid":"26023"},"id":"26023","arcs":[[160,-154,161,162]]},{"type":"Polygon","properties":{"name":"Ontonagon","geoid":"26131"},"id":"26131","arcs":[[163,-160,164,-146]]},{"type":"Polygon","properties":{"name":"Calhoun","geoid":"26025"},"id":"26025","arcs":[[-84,-53,-142,-152,-161,-58]]},{"type":"Polygon","properties":{"name":"Cass","geoid":"26027"},"id":"26027","arcs":[[-150,165,166,167]]},{"type":"Polygon","properties":{"name":"Sanilac","geoid":"26151"},"id":"26151","arcs":[[168,169,170,171,172]]},{"type":"MultiPolygon","properties":{"name":"Keweenaw","geoid":"26083"},"id":"26083","arcs":[[[173]],[[-156,174]],[[175]]]},{"type":"Polygon","properties":{"name":"Lapeer","geoid":"26087"},"id":"26087","arcs":[[-173,176,-114,177,178,179]]},{"type":"Polygon","properties":{"name":"Presque Isle","geoid":"26141"},"id":"26141","arcs":[[180,181,-78,-144]]},{"type":"MultiPolygon","properties":{"name":"Charlevoix","geoid":"26029"},"id":"26029","arcs":[[[-131,-145,-40,182,183]],[[184]],[[185]],[[186]],[[187]]]},{"type":"Polygon","properties":{"name":"Oakland","geoid":"26125"},"id":"26125","arcs":[[-178,-118,188,189,-36,190]]},{"type":"Polygon","properties":{"name":"Alcona","geoid":"26001"},"id":"26001","arcs":[[191,192,-85,193]]},{"type":"Polygon","properties":{"name":"Midland","geoid":"26111"},"id":"26111","arcs":[[-76,-127,194,195,-81]]},{"type":"Polygon","properties":{"name":"Ogemaw","geoid":"26129"},"id":"26129","arcs":[[196,-88,197,-73,-97]]},{"type":"Polygon","properties":{"name":"Saginaw","geoid":"26145"},"id":"26145","arcs":[[-126,198,199,200,201,-195]]},{"type":"Polygon","properties":{"name":"St. Clair","geoid":"26147"},"id":"26147","arcs":[[-172,202,-115,-177]]},{"type":"MultiPolygon","properties":{"name":"Mackinac","geoid":"26097"},"id":"26097","arcs":[[[203]],[[204]],[[205]],[[-92,206,207,208]]]},{"type":"Polygon","properties":{"name":"Shiawassee","geoid":"26155"},"id":"26155","arcs":[[-201,209,-34,210,-46,211]]},{"type":"MultiPolygon","properties":{"name":"Delta","geoid":"26041"},"id":"26041","arcs":[[[212]],[[213]],[[214,-121,215,216,-106]]]},{"type":"Polygon","properties":{"name":"Huron","geoid":"26063"},"id":"26063","arcs":[[-170,217,218]]},{"type":"Polygon","properties":{"name":"Grand Traverse","geoid":"26055"},"id":"26055","arcs":[[-136,219,220,-103,-5,-2]]},{"type":"MultiPolygon","properties":{"name":"Chippewa","geoid":"26033"},"id":"26033","arcs":[[[221]],[[222,-207,-91]]]},{"type":"Polygon","properties":{"name":"Baraga","geoid":"26013"},"id":"26013","arcs":[[223,224,225,-158]]},{"type":"Polygon","properties":{"name":"Tuscola","geoid":"26157"},"id":"26157","arcs":[[226,-218,-169,-180,227,-199,-125]]},{"type":"Polygon","properties":{"name":"Genesee","geoid":"26049"},"id":"26049","arcs":[[-228,-179,-191,-35,-210,-200]]},{"type":"Polygon","properties":{"name":"Dickinson","geoid":"26043"},"id":"26043","arcs":[[228,229,-104,230]]},{"type":"Polygon","properties":{"name":"Arenac","geoid":"26011"},"id":"26011","arcs":[[-198,-87,231,-123,-74]]},{"type":"Polygon","properties":{"name":"Wayne","geoid":"26163"},"id":"26163","arcs":[[-189,-117,232,-112,233]]},{"type":"Polygon","properties":{"name":"Alpena","geoid":"26007"},"id":"26007","arcs":[[-182,234,-192,-79]]},{"type":"Polygon","properties":{"name":"Marquette","geoid":"26103"},"id":"26103","arcs":[[-225,235,-122,-215,-105,-230,236]]},{"type":"Polygon","properties":{"name":"Schoolcraft","geoid":"26153"},"id":"26153","arcs":[[-93,-209,237,-216,-120]]},{"type":"Polygon","properties":{"name":"Iron","geoid":"26071"},"id":"26071","arcs":[[-159,-226,-237,-229,238,-147,-165]]},{"type":"Polygon","properties":{"name":"Kent","geoid":"26081"},"id":"26081","arcs":[[-65,-20,-56,-83,-11,-128,-108]]},{"type":"Polygon","properties":{"name":"Crawford","geoid":"26039"},"id":"26039","arcs":[[-43,239,-96,-102]]},{"type":"Polygon","properties":{"name":"Ingham","geoid":"26065"},"id":"26065","arcs":[[-47,-211,-39,-139,-51]]},{"type":"Polygon","properties":{"name":"Washtenaw","geoid":"26161"},"id":"26161","arcs":[[-37,-190,-234,-111,-23,-140]]},{"type":"Polygon","properties":{"name":"Antrim","geoid":"26009"},"id":"26009","arcs":[[-183,-44,-101,-221,240]]},{"type":"Polygon","properties":{"name":"St. Joseph","geoid":"26149"},"id":"26149","arcs":[[-59,-163,241,-167]]},{"type":"Polygon","properties":{"name":"Osceola","geoid":"26133"},"id":"26133","arcs":[[-7,-100,-71,-27,-62]]},{"type":"Polygon","properties":{"name":"Gratiot","geoid":"26057"},"id":"26057","arcs":[[-82,-196,-202,-212,-45,-18]]},{"type":"Polygon","properties":{"name":"Mason","geoid":"26105"},"id":"26105","arcs":[[-94,-64,-30,242]]},{"type":"Polygon","properties":{"name":"Oscoda","geoid":"26135"},"id":"26135","arcs":[[-80,-194,-197,-240]]},{"type":"Polygon","properties":{"name":"Van Buren","geoid":"26159"},"id":"26159","arcs":[[-14,-60,-166,-149,243]]}]}},"arcs":[[[5427,4745],[170,0],[152,-6]],[[5749,4739],[-3,-402]],[[5746,4337],[-519,8]],[[5227,4345],[12,47],[4,27],[-6,43],[-8,23],[-28,60],[-6,24],[3,35],[2,8],[8,11],[20,11],[75,22],[15,12],[49,0],[19,4],[21,16],[14,26],[6,18],[0,13]],[[5746,4337],[604,-1]],[[6350,4336],[-5,-134],[4,-401]],[[6349,3801],[-287,0]],[[6062,3801],[-320,-1]],[[5742,3800],[4,537]],[[5258,1650],[89,1],[13,0],[307,-2],[123,2]],[[5790,1651],[296,-1]],[[6086,1650],[3,-533]],[[6089,1117],[-276,-1]],[[5813,1116],[-637,-3]],[[5176,1113],[16,38],[15,56],[11,92],[7,39],[9,28],[3,18],[-5,66],[3,11],[14,30],[8,38],[1,4],[2,42],[-1,47],[-1,20],[0,8]],[[6065,2728],[596,-3]],[[6661,2725],[299,0]],[[6960,2725],[1,-268],[12,0],[-2,-267]],[[6971,2190],[-445,1],[-149,-1]],[[6377,2190],[1,135],[-1,135],[-312,0]],[[6065,2460],[0,268]],[[7563,581],[229,0],[60,-3]],[[7852,578],[155,3],[292,14]],[[8299,595],[14,-553]],[[8313,42],[-121,-3],[-26,-2],[-24,0],[-124,-5],[-26,0],[-143,-6],[-282,-10]],[[7567,16],[-4,565]],[[6065,3263],[592,-3]],[[6657,3260],[4,-535]],[[6065,2728],[0,535]],[[4980,3269],[491,-6]],[[5471,3263],[-2,-536]],[[5469,2727],[-528,8]],[[4941,2735],[-8,30],[-13,36],[-51,94],[-12,26],[-11,37],[-3,24],[0,18],[3,22],[12,29],[23,32],[36,41],[25,33],[21,38],[9,28],[8,41],[0,5]],[[7819,1664],[294,6]],[[8113,1670],[295,4]],[[8408,1674],[5,-135],[22,-407]],[[8435,1132],[-582,-10]],[[7853,1122],[-12,0]],[[7841,1122],[-22,542]],[[6946,5266],[153,-3],[0,134]],[[7099,5397],[459,-5]],[[7558,5392],[-6,-529]],[[7552,4863],[-594,5]],[[6958,4868],[-12,264],[0,134]],[[6971,2190],[586,-1]],[[7557,2189],[5,-527]],[[7562,1662],[0,-9],[-298,0]],[[7264,1653],[-293,1]],[[6971,1654],[0,536]],[[6675,1655],[296,-1]],[[7264,1653],[3,-535]],[[7267,1118],[-148,-1]],[[7119,1117],[-441,0]],[[6678,1117],[-3,538]],[[6675,1655],[-294,-2]],[[6381,1653],[-4,537]],[[6089,1117],[305,-3]],[[6394,1114],[0,-11],[7,-525]],[[6401,578],[-586,-3]],[[5815,575],[-2,541]],[[5466,3804],[276,-4]],[[6062,3801],[3,-538]],[[6065,3263],[-594,0]],[[5471,3263],[-1,11],[-2,257],[-2,273]],[[6065,2460],[-285,-2]],[[5780,2458],[-310,1],[-1,268]],[[6659,3800],[294,-5]],[[6953,3795],[304,-1]],[[7257,3794],[3,-532]],[[7260,3262],[-603,-2]],[[6657,3260],[2,540]],[[7257,3794],[291,0],[9,0]],[[7557,3794],[252,2]],[[7809,3796],[0,-254]],[[7809,3542],[-1,-263]],[[7808,3279],[-249,4],[0,-23],[-299,2]],[[7558,5392],[151,0]],[[7709,5392],[280,0],[176,6]],[[8165,5398],[-2,-66],[3,-198],[-12,-1],[2,-268]],[[8156,4865],[-405,-2],[-199,0]],[[7260,3262],[-2,-537]],[[7258,2725],[-298,0]],[[6086,1650],[295,3]],[[6678,1117],[-284,-3]],[[8158,4330],[710,5]],[[8868,4335],[1,-40],[-11,-64],[-1,-23],[3,-22],[4,-9],[0,-7],[-15,-50],[-2,-22],[3,-27],[-5,-12],[-9,-4],[-10,4],[-15,0],[-12,-7],[-35,-40],[-16,-12],[-6,-10],[-8,-24],[-5,-4],[-16,-7],[-4,13],[-22,8],[-20,2],[-26,-5],[-11,-5],[-20,-18],[-16,-21],[-14,-32],[-5,-26],[-1,-19],[-14,-53]],[[8560,3799],[-398,-3]],[[8162,3796],[-4,534]],[[5687,7403],[1,286]],[[5688,7689],[29,-2],[58,-13],[55,-5],[45,-1],[57,5],[55,-2],[47,-6],[56,-1],[41,2],[34,7],[141,52],[100,47],[41,14],[24,3]],[[6471,7789],[0,-785]],[[6471,7004],[-784,-1]],[[5687,7003],[0,400]],[[5466,3804],[-173,7],[-51,4],[-207,7]],[[5035,3822],[9,17],[21,28],[14,33],[10,31],[21,21],[14,32],[20,37],[39,58],[21,85],[5,31],[-1,21],[-4,26],[0,21],[4,28],[6,9],[6,19],[7,26]],[[6954,4334],[474,-1],[126,-5]],[[7554,4328],[3,-467],[2,-44],[-2,-23]],[[6953,3795],[-5,424],[6,115]],[[6350,4336],[604,-2]],[[6659,3800],[-310,1]],[[6352,4798],[20,17],[-14,42],[45,13],[555,-2]],[[6958,4868],[-4,-534]],[[6350,4336],[2,462]],[[3212,6198],[187,1],[0,271],[99,0],[1,134]],[[3499,6604],[311,-1]],[[3810,6603],[-1,-132],[54,-1],[-3,-536],[79,-1]],[[3939,5933],[-30,-74],[-22,-41],[-17,-16],[-17,-27],[-1,-8],[1,-8],[4,-8],[5,-3],[-2,-7],[-10,-15],[-19,-12],[-11,-12],[-6,-17],[-35,-30],[-9,-31],[-40,-50],[-7,-17],[-2,-19],[-33,-31],[-58,-75],[-46,-51],[-18,-11],[-28,-27],[-19,-30],[-11,-23],[-3,-14],[2,-14],[13,-17],[12,-10],[0,-2],[-2,-1],[-29,8],[-8,4],[-7,2],[-2,1],[-1,2],[-2,1],[-6,0],[-15,0],[-6,4],[-5,-2],[-4,0],[-1,1],[-1,7],[-7,8],[-5,3],[-1,2],[-8,14],[0,1],[3,5],[0,1],[-10,14],[-5,5],[-5,4],[-4,1],[-7,1],[-3,2],[-5,4],[-1,2],[-4,4],[-8,4],[-7,6],[-2,3],[-4,4],[-3,2],[-6,1],[-1,1],[0,1],[1,7],[-8,30],[0,2],[3,6],[4,4],[10,5],[2,2],[0,5],[-1,5],[0,5],[6,6],[1,6],[0,2],[-4,2],[0,3],[1,3],[7,7],[2,1],[4,0],[2,0],[1,2],[0,8],[3,14],[1,6],[-1,3],[7,11],[6,3],[0,4],[-1,7],[1,8],[6,9],[4,4],[4,10],[0,2],[10,12],[5,3],[10,13],[3,2],[2,1],[2,5],[0,8],[0,2],[2,2],[5,3],[10,13],[1,9],[-1,8],[-1,3],[-2,2],[-4,1],[-4,7],[1,6],[-1,7],[-1,2],[-20,13],[-1,1],[0,6],[-1,1],[-9,4],[-4,6],[-6,2],[-4,0],[-8,-3],[-5,-4],[-3,-3],[-2,-4],[-13,-5],[-19,-21],[-5,-7],[-1,-2],[-15,-5],[-1,-1],[0,-4],[-3,-4],[-10,-1],[-9,4],[-3,0],[-3,0],[-12,-2],[-6,4],[-3,2],[-12,0],[-12,-4],[-17,2],[0,-1],[-2,-2],[-2,0],[-4,2],[-4,1],[-3,-2],[-2,-7],[-1,-2],[-13,-7],[-2,0],[-2,1],[0,1],[2,4],[-1,4],[-3,3],[-7,2],[-3,1],[-3,3],[-2,3],[0,1],[-1,4],[-1,3],[-2,0],[-4,17],[0,4],[-5,5],[0,3],[2,4],[4,2],[7,4],[7,4],[3,8],[-3,5],[0,1],[0,3],[11,4],[2,3],[-1,9],[-1,3],[-1,2],[-6,5],[-5,11],[0,10],[-2,5],[0,2],[8,11],[10,4],[3,7],[11,4],[4,4],[1,2],[6,5],[8,3],[10,6],[0,3],[2,3],[7,8],[0,2],[-2,4],[1,3],[10,9],[0,3],[1,7],[2,5],[3,6],[1,2],[0,8],[-7,2],[-5,12],[-2,16],[-1,10],[1,5],[1,4],[0,2],[-5,8],[-8,8],[-6,5],[-11,6],[-6,5],[-1,1],[-1,4],[3,9],[3,1],[19,-5],[10,-4],[10,-1],[7,1],[2,2],[2,3],[1,3],[1,11],[0,9],[1,3],[1,1],[6,3],[5,4],[1,15],[-2,17],[-4,9],[-14,3],[-5,3],[0,5],[-1,3],[-9,8],[-7,15],[-9,8],[-6,2],[-3,3],[-1,9],[3,4],[0,3],[-1,3],[-1,3],[1,2],[25,6],[6,5],[4,2],[17,3],[1,1],[0,2],[0,8],[-2,4],[-6,6],[-18,11],[-4,3],[-5,6],[0,1],[5,5],[0,2],[-1,3],[-5,5],[-3,2],[-24,5],[-7,3],[-12,8]],[[5780,2458],[0,-135]],[[5780,2323],[-147,1],[1,-134],[-455,0]],[[5179,2190],[-11,27],[-44,91],[-100,186],[-15,34],[-34,90],[-17,54],[-17,63]],[[8299,595],[293,5]],[[8592,600],[148,3],[0,9],[158,1],[13,-7],[21,-32],[10,8],[6,-15],[32,-15],[24,-22],[30,-17]],[[9034,513],[5,-15],[-7,-18],[-4,-3],[-23,-1],[-1,-15],[-9,-11],[-8,1],[-7,-3],[-26,-23],[-9,-19],[-1,-14],[-15,-18],[-22,8],[-11,1],[-9,-3],[-16,-11],[-12,-17],[-10,-27],[-3,-27],[-7,-15],[-22,-19],[-9,-3],[-7,14],[-12,-6],[-18,-27],[-17,-35],[-16,-13],[-15,-5],[-6,-9],[-3,-7],[-2,-30],[7,-30],[13,-30],[4,-14],[-13,-6],[-22,-4],[-2,-3],[-55,-1],[-2,0],[-5,0],[-1,0],[-101,-4],[-1,0],[-10,0],[-2,0],[-51,-2],[-4,0],[-33,-1],[-24,-1],[-30,-2],[-67,-3]],[[9137,1836],[149,8]],[[9286,1844],[253,3],[53,3],[12,-295],[27,-35]],[[9631,1520],[-23,-1],[-34,-20],[-15,-22],[-19,-5],[-15,4],[-6,-1],[-20,-21],[-9,-22],[2,-15],[10,-9],[27,-11],[2,-8],[-2,-9],[1,-15],[9,-17],[-1,-11],[-3,-1],[-6,7],[-9,4],[-31,0],[-16,-5],[-15,-11],[-4,-8],[-2,-10],[-11,-11],[-1,-1],[-17,-27],[-10,-35],[-2,-45],[16,-31]],[[9427,1163],[-265,-7]],[[9162,1156],[-5,135],[-4,90],[-1,48],[-15,407]],[[4124,7388],[11,2],[11,11],[27,18],[39,7],[20,9],[16,12],[11,-1],[39,-9],[16,-16],[2,-10],[20,-39],[1,-9],[-4,-4],[3,-6],[24,-12],[30,3],[18,-12],[6,-12],[0,-14],[11,-7],[32,-5],[16,0],[26,6],[7,18],[2,17],[7,9],[19,17],[25,2],[23,1],[17,-6],[6,-6],[1,-5],[25,-36],[9,-9],[7,-1],[14,25],[-3,13],[3,13],[3,41],[-15,8],[-7,13],[-9,49],[17,17],[21,10],[3,-6],[7,-1],[18,3],[4,3],[32,-41],[-2,-24],[-4,-15],[-3,-6],[-8,-7],[-6,-13],[-1,-9],[12,-12],[12,-1],[8,10],[4,8],[7,6],[3,0],[3,-22],[-2,-13],[28,-11],[36,37],[41,28],[37,30],[14,17],[3,10],[15,14],[12,1],[19,-6],[10,1],[58,22],[51,23],[202,117],[33,24],[29,5],[23,-24],[10,-4],[15,0],[32,5],[46,15],[53,9],[51,5],[37,12],[58,10],[17,-1]],[[5687,7403],[-624,2],[-1,-268],[-312,2],[0,-269]],[[4750,6870],[-626,1]],[[4124,6871],[0,517]],[[7809,3542],[151,0],[1,-132],[170,-1]],[[8131,3409],[-3,-26],[-9,-57],[-10,-106],[-4,-16],[-20,-27],[-12,2],[-1,-3],[2,-13],[19,-54],[37,-66],[15,-13],[56,-30],[28,42],[15,3],[22,-50],[55,-16],[32,-12],[39,-33]],[[8392,2934],[0,-56],[1,-133]],[[8393,2745],[-149,0],[1,67],[-124,0],[-168,2],[1,67],[-147,2]],[[7807,2883],[1,396]],[[5780,2323],[3,-268],[8,-269],[-1,-135]],[[5258,1650],[-3,25],[-1,76],[1,40],[-4,37],[-3,55],[-12,106],[-8,43],[-15,52],[-7,12],[0,15],[-6,25],[-21,54]],[[7102,6299],[0,-767]],[[7102,5532],[-290,3],[-1,-31],[-46,2],[-21,27],[-5,31],[-29,38],[-63,1],[1,48]],[[6648,5651],[51,-4],[15,-4],[13,0],[13,8],[79,14],[54,27],[4,15],[-1,10],[-4,12],[-7,7],[-74,11],[-11,-2],[-1,-4],[-5,-3],[-58,21],[-35,34],[-24,28],[-26,68],[-8,28],[-5,45],[1,10],[9,16],[23,22],[17,26],[5,11],[1,8],[17,16],[57,19],[11,7],[7,7],[6,13],[32,26],[34,37],[4,18],[-2,10],[-11,13],[-39,23],[-26,3],[-11,6],[-3,4],[8,4],[16,-5],[71,0],[17,-4],[18,-11],[54,3],[32,-11],[43,2],[9,2],[13,8],[10,13],[2,13],[-16,14],[-1,3],[16,10],[9,4],[27,-11],[12,3],[10,6],[2,-1]],[[5777,5828],[13,15],[9,-2],[8,-15],[0,-19],[-3,-12],[-19,18],[-8,15]],[[5665,5769],[31,-5],[29,-18],[11,-37],[-9,-40],[-50,66],[-12,34]],[[5437,5302],[7,19],[12,9],[7,2],[14,-2],[34,-4],[16,-4],[5,-3],[16,-20],[0,-27],[-5,-12],[-5,-40],[2,-9],[7,-12],[0,-16],[-25,-10],[-20,12],[-8,12],[-22,23],[-19,13],[-8,9],[-2,5],[-6,55]],[[5968,4740],[-219,-1]],[[5427,4745],[2,41],[7,26],[0,20],[-6,47],[-2,30],[2,17],[5,15],[10,8],[26,8],[9,-13],[12,-7],[15,-5],[21,1],[15,9],[10,13],[7,23],[7,9],[11,8],[13,21],[4,16],[9,6],[20,0],[22,-10],[8,-7],[15,-22],[12,-6],[20,-2],[22,3],[26,9],[10,6],[34,43],[3,8],[2,27],[6,23],[12,13],[19,42],[7,7],[36,15],[21,17],[18,25],[7,20],[1,16],[23,46],[47,63],[7,-3],[2,-6],[5,-4],[18,0],[9,3],[26,19],[4,12],[13,16],[14,-1],[17,-32],[-6,-19],[-7,-6],[-19,-9],[-12,-13],[0,-3],[-2,-2],[-1,-2],[-1,-1],[-2,0],[-2,0],[-3,2],[-4,1],[-21,-4],[-12,-6],[-18,-33],[7,-22],[32,-65],[12,-4],[10,-14],[-1,-24],[-5,-4],[-4,3],[-8,18],[-12,-4],[-9,-18],[-3,-29],[-12,-13],[-16,-14],[-10,-3],[-7,-14],[-17,-29],[9,-10],[10,-2],[16,12],[18,25],[3,1],[2,-26],[1,-73],[-25,-6],[-5,-3],[-18,-48],[-7,-10],[-4,-15],[-4,-38],[1,-27],[12,-32],[6,-32],[-5,-22],[1,-1]],[[5323,5103],[3,11],[16,34],[4,5],[25,8],[31,-11],[18,-16],[-18,1],[-5,-2],[-4,-6],[-2,-5],[1,-8],[10,-15],[-28,-14],[-22,-3],[-27,8],[-2,13]],[[7267,1118],[294,4],[280,0]],[[7853,1122],[-4,-394],[3,-150]],[[7563,581],[-433,-5]],[[7130,576],[-11,541]],[[7102,6299],[8,-1],[9,-14],[3,-18],[43,-15],[3,-11],[43,-14],[50,-29],[39,-17],[23,-12],[3,-6],[17,-13],[97,-58],[24,3],[9,15],[10,8],[17,0],[17,-9],[30,-12],[58,13],[50,-17],[24,-13],[69,-15],[14,-12]],[[7762,6052],[-60,-2],[3,-529],[4,-129]],[[7099,5397],[3,135]],[[661,7805],[33,-1],[-2,-265],[155,-1],[-2,-134],[470,0],[0,-265],[444,-1],[24,1]],[[1783,7139],[0,-363]],[[1783,6776],[-126,63],[-42,9],[-46,12],[-6,1],[-35,8],[-8,2],[-3,1],[-3,1],[-15,4],[-2,0],[-71,17],[-274,65],[-47,12],[-131,30],[-37,10],[-121,28],[-179,43],[-2,0],[-11,2],[-13,3],[-239,58],[-1,0],[0,2],[2,2],[1,4],[-1,3],[-1,1],[0,2],[1,3],[3,2],[0,2],[0,7],[-2,6],[-1,1],[-2,0],[-1,0],[-1,2],[0,2],[0,2],[-5,5],[-5,3],[-4,4],[-1,5],[3,10],[-2,1],[-2,0],[-5,5],[-6,8],[-3,10],[-2,4],[-6,3],[-6,12],[-1,7],[1,10],[-1,4],[-6,18],[-4,5],[0,2],[0,1],[-10,0],[-4,1],[-2,19],[-1,6],[-11,4],[-2,1],[-3,5],[1,4],[4,2],[1,2],[-1,1],[-5,5],[-11,6],[-3,3],[-9,19],[-4,12],[0,3],[-2,2],[-5,3],[-2,0],[-8,-3],[-2,0],[-1,3],[0,2],[2,5],[-1,3],[-2,0],[-6,-4],[-9,-3],[-3,-1],[-3,1],[-11,-1],[-2,-2],[-2,-1],[-3,0],[-3,2],[0,2],[0,1],[-2,2],[-2,0],[-2,0],[-1,1],[0,2],[0,2],[1,2],[-6,5],[4,7],[-1,2],[-6,5],[-1,-1],[-1,-2],[-6,-5],[-3,0],[-9,3],[-1,-2],[0,-1],[-5,-2],[-7,0],[-4,1],[-1,0],[-6,-2],[-2,-1],[-4,1],[-1,7],[5,3],[3,8],[2,12],[-1,4],[-12,11],[-5,-1],[-3,1],[-1,3],[0,3],[-5,5],[-7,1],[-9,-3],[-4,-8],[-2,-14],[-1,-1],[-2,0],[-2,1],[-3,4],[-2,0],[-5,2],[-11,-2],[-5,-2],[-16,-8],[-8,-2],[-2,2],[-1,4],[-4,10],[-1,2],[-1,0],[-2,0],[-4,5],[-3,7],[-8,8],[-1,0],[-1,9],[-3,4],[87,54],[26,11],[26,-8],[52,24],[34,9],[92,33],[80,15],[69,20],[21,9],[40,29],[13,16],[15,11],[21,10],[48,36],[33,35],[4,4]],[[5063,842],[176,1],[1,-265]],[[5240,578],[-4,-480]],[[5236,98],[-49,1],[-295,-1],[-22,0],[-6,0],[-145,0],[-1,0],[-1,0],[-131,0],[-2,0],[-65,1],[-1,0],[-1,0],[-3,0],[-24,0],[-2,0],[60,37],[75,54],[47,39],[75,75],[27,38],[19,37],[33,89],[68,130],[14,32],[6,20],[24,25],[78,95],[23,32],[26,40]],[[6984,579],[146,-3]],[[7567,16],[-1,0],[-45,-1],[-3,0],[-48,-1],[-390,-11],[-70,-3],[0,18],[0,20],[0,19],[0,7],[0,8],[0,27],[-16,-1],[-8,0]],[[6986,98],[-2,481]],[[1855,8215],[11,15],[13,27],[13,41],[18,22],[42,21],[9,2],[42,40],[31,15],[15,-1],[17,8],[43,47],[37,29],[35,22],[20,10],[20,2],[21,8],[17,10],[31,6],[13,5],[77,62]],[[2380,8606],[267,0],[1,-133],[88,0]],[[2736,8473],[-2,-1],[-9,-15],[-7,-22],[-1,-26],[4,-11],[4,-3],[6,1],[-1,-6],[-9,-10],[-10,-5],[-2,0],[-2,6],[-5,6],[-10,2],[-11,-3],[-12,-8],[-10,-13],[0,-5],[2,-2],[1,-7],[-2,-9],[-11,-25],[-53,-28],[-9,-1],[-4,-5],[-4,-11],[-1,-17],[-6,-28],[-11,-32],[-8,-11],[-14,-12],[-24,-32],[-8,-8],[-41,-9],[-6,-39],[-3,-12]],[[2457,8072],[-126,-1],[0,-134],[-159,0],[0,-664]],[[2172,7273],[-390,-1]],[[1782,7272],[2,401],[157,-1],[0,132],[-85,-1],[-1,412]],[[6401,578],[583,1]],[[6986,98],[-134,0],[-35,0],[-1,0],[-13,0],[-1,-1],[-82,1],[-2,0],[-97,0],[-7,0],[-62,0],[-30,0],[-45,0],[-49,0],[-1,0],[-1,0],[-23,0]],[[6403,98],[-2,480]],[[661,7805],[50,46],[21,13],[52,22],[88,18],[58,5],[16,-4],[23,-8],[9,-9],[20,-1],[62,20],[42,6],[27,9],[19,0],[10,-5],[24,-2],[43,3],[28,7],[54,21],[153,71],[27,14],[33,28],[41,53],[32,30],[18,12],[13,3],[6,-8],[9,-4],[24,-2],[30,5],[29,17],[13,2],[8,-9],[30,0],[14,3],[18,8],[17,10],[19,17],[14,19]],[[1782,7272],[1,-133]],[[5240,578],[575,-3]],[[5815,575],[3,-417],[-11,-21],[-21,-12],[-7,-28]],[[5779,97],[-101,0],[-3,0],[-18,1],[-107,0],[-21,0],[-62,1],[-27,0],[-78,0],[-3,0],[-112,-1],[-11,0]],[[9115,2511],[21,0],[-17,536]],[[9119,3047],[639,23]],[[9758,3070],[1,-17],[-1,-15],[7,-102],[3,-20],[5,-13],[10,-58],[25,-63],[0,-9],[15,-51],[18,-41],[1,-9],[-2,-14],[6,-84],[-2,-30],[9,-23],[1,-27],[-4,-16],[11,-124],[5,-19],[13,-25],[7,-43]],[[9886,2267],[-616,-22]],[[9270,2245],[-5,201],[-148,-2],[-2,67]],[[3455,8806],[18,7],[17,9],[41,-4],[6,-8],[-17,-17],[-22,0],[-27,4],[-16,9]],[[2380,8606],[15,11],[29,31],[9,22],[14,19],[50,48],[37,20],[82,30],[25,13],[23,16],[58,11],[14,8],[12,10],[1,6],[-1,5],[45,14],[39,4],[14,4],[68,9],[11,-1],[34,3],[1,0],[0,8],[10,1],[77,6],[62,-1],[33,-3],[6,-3],[101,-5],[20,2],[55,-19],[33,-18],[18,-14],[7,-52],[-2,-8],[-11,0],[-27,7],[-11,-1],[-10,-3],[-7,-7],[-44,-10],[-19,-11],[-15,2],[-9,7],[-17,6],[-11,1],[-31,0],[-75,-8],[-19,-4],[-10,-20],[-1,-9],[4,-9],[10,-9],[9,-2],[11,-14],[1,-7],[-7,-9],[-4,-3],[-15,0],[-12,-3],[-26,-15],[-34,-25],[-48,-12],[-7,-4],[-14,-14],[-32,-39],[-15,-4],[-10,-6],[-18,-24],[-39,-36],[-39,-10],[-13,2],[-10,-2],[-19,-15]],[[1453,9514],[10,19],[26,11],[7,8],[-1,11],[8,9],[45,33],[104,51],[96,37],[31,16],[66,26],[12,3],[5,-3],[15,2],[25,13],[-1,4],[3,5],[73,33],[24,1],[7,-3],[29,12],[19,12],[0,13],[10,9],[25,12],[20,14],[28,14],[13,-1],[14,8],[11,7],[-1,7],[2,4],[22,18],[53,24],[45,12],[39,19],[28,-15],[30,5],[11,11],[12,7],[28,6],[16,-1],[31,12],[5,-16],[-2,-15],[-9,-6],[-28,-6],[-13,-7],[-12,-9],[-20,-23],[-33,-25],[-69,-43],[-14,-14],[0,-10],[3,-4],[3,-10],[-2,-7],[-6,-9],[-113,-72],[-60,-25],[-67,-22],[-25,-3],[-50,-22],[-26,1],[-58,-19],[-23,-12],[-7,-11],[-49,-23],[-50,-23],[-3,-18],[13,-8],[29,5],[22,-7],[68,19],[1,-3],[-16,-14],[-109,-37],[-30,-14],[-27,-4],[-15,-5],[-65,-26],[-20,-11],[-42,-7],[-40,12],[-3,3],[0,11],[-12,14],[-41,3],[-1,3],[1,2],[8,4],[-23,20],[-5,-1],[-5,9]],[[9270,2245],[16,-401]],[[9137,1836],[-438,-13]],[[8699,1823],[-9,528]],[[8690,2351],[0,15],[136,3],[-3,135],[292,7]],[[7762,6052],[10,-9],[19,-26],[29,-29],[22,-18],[14,-18],[3,-9],[-1,-21],[6,-29],[7,-17],[9,-12],[17,-12],[25,-10],[25,-2],[20,7],[4,3],[10,2],[24,-3],[14,-6],[25,4],[49,-1],[37,-12],[34,-27],[29,-33],[22,-17],[43,-25],[23,-4],[19,1],[22,-10],[23,0],[19,4],[31,-27],[36,-17],[31,-20],[55,-30],[36,-8],[25,6],[5,2],[1,9],[9,0],[23,-17],[7,-1],[22,17],[10,-3],[14,-21],[40,-48],[16,-11],[10,-11],[3,-9],[27,-17],[16,-4],[4,-4],[4,-8],[-8,-22],[-31,-14],[1,-11],[8,-18],[23,-31]],[[8782,5405],[-158,0],[-459,-7]],[[6946,5266],[-458,2],[1,135],[-205,3]],[[6284,5406],[-2,43],[21,54],[21,19],[25,17],[14,14],[20,16],[16,5],[7,-4],[20,2],[13,6],[10,10],[4,8],[20,13],[33,27],[16,6],[18,0],[48,15],[60,-6]],[[6275,6285],[22,53],[20,7],[12,-34],[-10,-29],[-22,-12],[-22,15]],[[6113,6364],[34,-12],[58,-39],[0,-31],[-15,-16],[-56,19],[-31,30],[10,49]],[[5981,6007],[12,41],[14,11],[6,12],[-1,12],[-5,17],[5,36],[5,11],[13,14],[9,4],[14,17],[9,29],[0,23],[-3,8],[-1,11],[2,4],[21,-5],[7,-9],[11,-1],[13,0],[23,6],[7,0],[4,-13],[-8,-5],[-6,-1],[-8,-10],[5,-2],[16,-12],[5,-33],[1,-10],[-11,-12],[-5,-15],[3,-16],[5,-10],[12,-19],[4,-47],[-5,-18],[-22,-20],[-11,-6],[-12,-2],[-4,-3],[-4,-17],[-9,-5],[-26,-5],[-70,16],[-6,6],[-9,18]],[[5891,6220],[16,17],[46,-6],[4,-32],[-29,-40],[-31,1],[-6,60]],[[9162,1156],[-86,-1],[-64,-2],[-142,-5],[-64,-2],[-9,0],[-73,-2],[-148,-6]],[[8576,1138],[-141,-6]],[[8408,1674],[-3,135],[294,14]],[[8156,4865],[709,4]],[[8865,4869],[0,-9],[8,-16],[17,-20],[7,-56],[-2,-53],[-2,-6],[1,-13],[9,-26],[8,-12],[13,-12],[-4,-38],[-16,-56],[-22,-35],[-9,-33],[-1,-21],[2,-47],[6,-25],[0,-13],[-12,-39],[0,-4]],[[8158,4330],[-2,535]],[[7807,2883],[-3,-134],[-249,0],[0,-24]],[[7555,2725],[-297,0]],[[7554,4328],[604,2]],[[8162,3796],[-353,0]],[[8393,2745],[0,-133],[4,-103],[0,-161]],[[8397,2348],[-295,-1],[3,-135]],[[8105,2212],[-548,-7]],[[7557,2205],[-2,520]],[[9886,2267],[2,-11],[10,-27],[4,-40],[6,-24],[18,-23],[18,-40],[43,-82],[8,-4],[-8,-9],[-2,-4],[0,-6],[1,-7],[4,-7],[9,-11],[-5,-16],[-15,-22],[-23,-22],[-10,-17],[-11,-39],[-7,-22],[0,-9],[2,-35],[-1,-10],[-5,-24],[-7,-18],[-4,-25],[0,-5],[2,-5],[11,-28],[5,-23],[0,-11],[-20,-44],[-1,-24],[-13,-26],[-20,-55],[1,-43],[-11,-36],[-6,-10],[-31,-24],[-2,-2],[-5,-10],[-3,-2],[-17,-14],[-9,-10],[-3,-3],[-6,-17],[-7,-5],[-18,-4],[-3,1],[-5,2],[-8,7],[-10,4],[-10,-1],[-10,-3],[-2,-1],[-8,-6],[-16,-13],[-6,-10],[-15,-20],[-10,-6],[4,57],[-11,4],[14,26],[-10,21],[-17,-4],[-10,8],[-3,10],[15,14],[18,-1],[9,9],[-3,10],[-10,10],[0,3],[18,0],[14,1],[-5,18],[19,17],[16,-13],[12,0],[9,19],[-3,21],[-19,11],[-15,-4],[-8,10],[-18,13],[-14,4],[-20,-1],[-6,-9],[-2,0]],[[7289,6569],[10,12],[13,-7],[3,-11],[-7,-18],[-11,12],[-8,12]],[[7217,6593],[9,10],[19,-19],[9,-11],[-11,-11],[-17,-11],[-9,11],[0,31]],[[7203,6415],[6,33],[6,2],[15,-5],[9,-8],[18,-24],[7,-15],[17,-40],[13,-9],[50,-19],[30,4],[27,-8],[76,-28],[7,2],[6,7],[2,11],[-2,9],[3,1],[10,-14],[10,-20],[59,-19],[0,-4],[-18,-20],[-2,-16],[-28,-17],[-1,-3],[2,-8],[-15,-8],[-17,-1],[-13,7],[-27,2],[-22,7],[-19,-3],[-21,10],[-8,12],[-2,15],[-20,15],[-31,39],[-15,10],[-25,10],[-7,6],[-4,10],[-8,15],[-19,17],[-15,20],[-6,5],[-13,4],[-14,10],[-1,6]],[[6471,7004],[155,0],[1,-135],[936,0],[0,-133],[155,0],[0,-133],[156,0],[0,-10]],[[7874,6593],[-33,-5],[-39,-14],[-8,5],[-75,-3],[-21,-18],[-94,1],[-29,-23],[-28,-15],[-66,41],[-11,24],[-7,6],[-25,-14],[-21,14],[-4,7],[1,5],[-2,4],[-29,4],[-8,-6],[0,-24],[-14,-4],[-9,1],[-3,5],[0,8],[5,21],[-4,22],[-9,21],[-4,5],[-25,15],[-21,-2],[-7,-7],[-28,0],[-48,35],[-11,5],[-13,-3],[-11,-7],[-15,-17],[-7,-12],[0,-16],[8,-58],[3,-3],[-1,-6],[-3,-3],[-21,-1],[-23,-5],[-9,-10],[-11,-23],[-1,-7],[8,-13],[18,-9],[6,-11],[1,-6],[-26,-14],[16,-51],[7,-12],[18,-20],[-2,-4],[-5,-3],[-18,-1],[-2,-2],[-4,-15],[-26,-2],[-58,35],[-48,21],[-9,15],[1,11],[-5,14],[-14,3],[-25,15],[-8,9],[-29,12],[-18,11],[-25,39],[-45,47],[-38,30],[-13,8],[-52,19],[-41,8],[-18,6],[-34,21],[-13,5],[-14,2],[-48,-5],[-9,-4],[-31,24],[-55,8],[-27,10],[-35,22],[-25,10],[-25,-1],[-13,-8],[-19,-8],[-15,21],[-23,9],[-19,1],[-18,-10],[-1,-2],[3,-2],[-9,-12],[-42,17],[-24,1],[-16,-3],[-11,-6],[-24,-18],[-79,-75],[-17,-34],[-38,-38],[-8,-16],[-12,-10],[-41,-10],[-34,8],[-24,-1],[-34,10],[-25,9],[-25,4],[-9,-1],[-10,-5],[-8,-13],[-13,-4],[-23,5],[-5,0]],[[5687,6577],[0,426]],[[8105,2212],[3,-407],[5,-135]],[[7819,1664],[-257,-2]],[[7557,2189],[0,16]],[[4654,6037],[19,-6],[14,-11],[27,-32],[22,-19],[8,-17],[-2,-9],[-19,-22],[-15,2],[-15,47],[-38,34],[-26,23],[25,10]],[[4536,5879],[21,2],[15,-18],[9,-31],[-16,-16],[-24,20],[-10,23],[5,20]],[[3810,6603],[156,0],[2,268],[156,0]],[[4750,6870],[156,-1],[0,-403],[39,0],[-1,-213]],[[4944,6253],[-8,3],[-16,-4],[-9,-16],[-12,4],[-10,8],[-13,-3],[-5,-7],[-6,-18],[-2,-24],[-11,-15],[-5,-4],[-5,0],[-36,12],[-13,-7],[-6,-10],[1,-36],[-3,-24],[-8,-1],[-22,7],[-11,-5],[-6,-5],[-4,-7],[14,-59],[0,-21],[-9,10],[-11,7],[-19,-3],[-22,9],[-27,19],[-2,9],[-8,12],[-16,2],[-12,29],[-1,14],[3,10],[14,11],[20,-5],[16,7],[13,16],[0,10],[-4,3],[-3,15],[11,13],[19,5],[18,23],[-2,25],[4,28],[17,3],[7,-7],[18,-6],[18,5],[8,15],[-5,5],[-1,5],[6,10],[7,6],[10,-1],[8,6],[2,8],[-5,13],[5,15],[7,7],[5,0],[9,6],[12,20],[1,6],[-2,27],[-4,12],[-11,12],[-15,10],[-18,6],[-19,-3],[-12,-21],[-13,-13],[-13,-1],[-15,-12],[-9,-12],[1,-26],[-17,-15],[-94,18],[-9,5],[-18,25],[-9,4],[-11,0],[-29,-11],[-3,-9],[2,-38],[7,-4],[3,-9],[2,-15],[-16,-26],[-20,-23],[-25,-15],[-2,-7],[3,-7],[-1,-6],[-21,-23],[-4,-20],[4,-11],[-40,-18],[-8,2],[-23,0],[-11,-3],[-21,-18],[-29,-3],[-25,-36],[-3,4],[-1,15],[-3,11],[-14,7],[-4,14],[2,22],[6,13],[3,38],[-7,20],[-1,40],[-8,28],[-21,33],[-17,11],[-16,-3],[-10,-4],[-16,-19],[-6,-15],[-2,-17],[1,-34],[-7,-20],[-1,-11],[3,-9],[8,-3],[3,-5],[-5,-17],[-6,-6],[-10,-22],[13,-16],[-45,-11],[-5,-4],[0,-5],[-15,-15],[-22,-6],[-54,-31],[-30,-39],[-34,-57],[-14,-16],[-36,-57],[-1,-3]],[[9119,3047],[-436,-12],[-1,95],[-7,3]],[[8675,3133],[-3,7],[-16,12],[-10,44],[21,33],[19,26],[1,25],[18,27],[0,23],[20,40],[24,-12],[-12,-33],[7,-21],[31,11],[26,14],[30,16],[20,39],[-21,8],[-31,8],[-34,7],[-8,16],[40,-1],[71,-2],[16,8],[29,24],[17,27],[9,20],[0,7],[43,12],[39,3],[19,-2],[44,12],[13,5],[18,12],[16,4],[36,-3],[16,3],[9,5],[16,14],[20,39],[7,6],[32,3],[10,3],[29,27],[11,-1],[3,-4],[11,-1],[24,11],[16,1],[32,-30],[18,-9],[53,-12],[50,-21],[6,-15],[7,-7],[22,-4],[24,-16],[9,-10],[13,-26],[20,-36],[3,-2],[21,-46],[18,-53],[29,-24],[15,-24],[1,-10],[-6,-2],[0,-3],[4,-8],[13,-10],[20,-96],[-1,-20],[2,-14],[6,-11],[8,-76]],[[5968,4740],[5,-6],[10,-5],[22,-4],[14,1],[7,4],[3,24],[12,37],[45,86],[16,14],[3,26],[-29,2],[-7,-5],[-6,11],[30,33],[8,14],[17,53],[-3,10],[3,11],[34,25],[22,2],[6,-16],[7,-31],[-2,-3],[-7,1],[-17,-9],[-7,-40],[-2,-30],[5,-10],[-11,-56],[-6,-15],[-8,-12],[-13,-4],[-26,-17],[-20,-24],[-5,-13],[0,-31],[-21,-46],[7,-7],[21,-10],[20,-3],[14,2],[28,30],[1,8],[-1,13],[-5,9],[12,25],[31,18],[14,15],[3,16],[23,38]],[[6215,4871],[76,-1],[8,-46],[33,-3],[20,-23]],[[8005,6782],[27,-5],[5,-15],[12,-10],[1,-26],[-28,17],[-21,17],[4,22]],[[6471,7789],[80,13],[137,-9],[34,4],[34,13],[25,5],[31,1],[13,-3],[3,-2],[-45,-37],[-25,-27],[-16,-24],[-9,-23],[-3,-20],[2,-15],[-9,-77],[-2,-37],[2,-30],[5,-20],[3,-22],[2,-1],[3,-11],[-2,-5],[-23,-8],[-10,-8],[-3,-9],[1,-19],[6,-16],[20,-25],[11,-7],[13,-6],[57,-5],[17,6],[10,11],[13,3],[4,-14],[15,-16],[9,-3],[27,-4],[23,3],[17,4],[14,-14],[8,-18],[18,-7],[36,3],[39,11],[57,23],[42,24],[14,6],[31,-9],[29,4],[18,-20],[10,-23],[20,-17],[-9,-8],[-6,-13],[4,-12],[6,-14],[16,-2],[40,7],[60,32],[12,2],[18,-12],[9,3],[12,10],[9,20],[0,13],[-10,8],[23,33],[31,18],[32,-2],[24,14],[2,1],[38,-2],[7,-4],[15,-8],[41,-11],[21,0],[13,2],[2,1],[12,9],[35,51],[41,9],[20,-20],[14,-1],[17,3],[8,5],[9,1],[13,-3],[7,-14],[6,-5],[9,-21],[-17,-52],[-27,-80],[9,-71],[25,-54],[16,-23],[-17,-11],[5,-72],[23,-18],[-13,-24],[-13,-11],[-8,-2],[-12,-1],[-15,-11],[-1,-1],[-3,0],[-2,0],[-1,0],[0,1],[0,2],[-1,3],[-9,8],[-29,3],[-45,-5],[-17,-12],[-21,-27],[5,-22],[-3,-19],[-4,-6],[38,-20],[30,5],[24,27],[7,-3],[59,-3],[12,-9],[2,-8],[17,-28],[5,-5],[8,-2],[36,0],[43,-22],[-6,-13],[-10,3],[-16,-9],[-12,-9],[-10,-15],[-4,-11],[1,-7],[7,-7],[18,-13],[30,-38],[27,-15],[21,-19],[32,-7],[15,2],[10,3],[6,-3],[4,-14],[6,-4],[28,-9],[10,-20],[34,-8],[6,2],[29,47],[19,-5],[15,-30],[30,-11],[22,13],[14,22],[0,21],[-11,30],[-28,8],[-20,26],[-15,47],[11,7],[4,0],[24,-10],[16,-13],[11,-4],[19,2],[35,-2],[6,4],[5,11],[20,4],[53,-5],[33,6],[11,-3],[13,-9],[21,-9],[22,-1],[6,-9],[4,-14],[1,-7],[9,-13],[14,-4],[8,-17],[5,-17],[3,-24],[10,-16],[48,-18],[8,0],[9,-5],[9,-12],[1,-6],[-11,-19],[-9,-5],[-27,-61],[-8,-9],[-12,-7],[-44,-10],[-27,6],[-61,25],[-32,20],[-37,-16],[-40,-2],[-17,6],[-12,1],[-29,-5],[-4,-5],[-21,2],[-19,7],[-3,9],[-6,3],[-18,-2],[-6,-5],[-10,1],[-7,17],[-6,1],[-24,10],[-18,10],[-2,3],[-37,-4],[-13,-12],[-39,12],[-41,2],[-14,-8],[-26,-4],[-78,18],[-13,-5],[-19,8],[-2,7],[-5,2],[-4,0]],[[2457,8072],[-5,-25],[-26,-57],[-3,-55],[-7,-29],[2,-8],[11,-31],[14,-30],[-25,-6],[-18,-28],[0,-12],[25,-11],[27,15],[21,42],[6,11],[23,28],[37,34],[4,18],[-27,3],[18,30],[21,8],[5,-23],[24,5],[49,45],[36,26],[25,13],[21,22],[97,45],[14,10],[15,2],[13,-7],[-21,-28],[-47,-38],[-30,-16],[-21,-16],[-18,-20],[-10,-22],[-40,-60],[-1,-14],[20,-2],[20,34],[12,25],[39,37],[45,32],[16,0],[44,8],[32,11],[24,5],[21,-3],[26,-9]],[[2965,8031],[0,-227],[66,0],[0,-133],[-155,-1],[-1,-398]],[[2875,7272],[-703,1]],[[8392,2934],[20,-17],[45,21],[50,55],[30,44],[2,2],[24,27],[22,30],[21,11],[7,5],[6,2],[3,-2],[3,-6],[19,-9],[22,13],[10,20],[-1,3]],[[8690,2351],[-293,-3]],[[2874,6505],[0,501]],[[2874,7006],[626,0],[-1,-402]],[[3212,6198],[-11,8],[-11,15],[0,9],[1,0],[-1,4],[-5,6],[-6,2],[-3,5],[-5,2],[-4,-1],[-12,-1],[-5,-2],[-3,0],[-2,1],[-1,5],[-2,2],[-2,2],[-2,0],[-2,0],[-2,-1],[-16,-2],[-6,4],[-3,1],[-7,-3],[-12,-1],[-13,1],[-6,-2],[-5,2],[-2,2],[1,2],[-3,5],[-7,3],[-6,1],[-12,4],[4,8],[2,1],[1,3],[-2,9],[-7,15],[-2,3],[-2,1],[-5,0],[-8,-2],[-6,-3],[-14,0],[-7,-3],[-5,-2],[-4,0],[-4,1],[-7,0],[-1,-1],[-1,-4],[-4,-4],[-5,-2],[-3,-2],[-9,-1],[-18,0],[-5,2],[-2,4],[-2,1],[-11,-1],[-7,2],[-7,7],[-5,2],[-3,9],[1,2],[0,2],[-3,4],[-2,2],[-9,0],[-16,8],[-3,3],[-6,12],[2,4],[1,3],[8,6],[6,4],[3,5],[8,7],[3,2],[3,1],[3,2],[11,14],[11,9],[2,3],[3,7],[3,4],[1,0],[6,-2],[3,2],[2,11],[-1,5],[-10,8],[-2,1],[-15,-2],[-6,2],[-2,4],[-4,20],[-1,1],[0,5],[0,6],[2,4],[3,5],[4,3],[4,2],[0,2],[-1,4],[-8,7],[-2,0],[-14,0],[-2,-1]],[[8560,3799],[-3,-12],[-2,-45],[2,-11],[-7,-28],[-19,-23],[-4,-11],[1,-15],[8,-20],[-21,-3],[-25,2],[-36,-5],[-37,-25],[-10,-24],[9,-41],[-16,-8],[-43,19],[-20,-15],[-4,-4],[-21,-6],[-30,0],[-52,6],[-24,-11],[-8,-7],[-2,-7],[-16,-19],[-11,-2],[-9,-19],[-6,-19],[-1,-17],[-21,-8],[-1,-12]],[[9427,1163],[1,-1],[-20,-66],[-3,-15],[-7,-14],[-5,-6],[-21,-11],[-5,-6],[-12,-23],[6,-11],[-27,-7],[-18,-12],[-36,-11],[-37,-4],[-57,-19],[-20,-14],[-21,-28],[-2,-7],[-16,-39],[-21,-33],[-1,-7],[-7,-92],[16,-76],[-15,-57],[-30,-4],[-14,-19],[-25,-11],[0,-7],[2,-1],[2,-14],[-3,-32],[3,-3]],[[8592,600],[-3,136],[-2,136],[-5,134],[-6,132]],[[8782,5405],[4,-5],[3,0],[16,-33],[1,-15],[6,-9],[4,-6],[14,-2],[14,-22],[27,-8],[0,-3],[-4,-4],[1,-13],[13,-46],[12,-13],[9,-33],[0,-10],[14,-26],[4,-2],[7,-10],[7,-17],[-7,-6],[-21,5],[-18,9],[-47,14],[-22,14],[-12,18],[-40,13],[-43,-20],[-10,-10],[-15,-24],[-1,-5],[10,-24],[14,-7],[5,-6],[-6,-13],[-4,0],[-13,-15],[8,-58],[6,-18],[7,-12],[10,-9],[25,-13],[8,-19],[6,-5],[51,-26],[40,-8],[0,-34]],[[2965,8031],[15,-6],[35,-3],[23,-1],[37,4],[70,1],[32,-26],[36,-13],[6,0],[17,9],[13,2],[5,-5],[25,-11],[13,-1],[7,-5],[1,-7],[-3,-3],[2,-6],[14,-8],[12,-1],[12,7],[7,0],[8,-23],[-3,-5],[3,-16],[4,-8],[5,-6],[17,-3],[24,2],[11,9],[-3,10],[1,4],[8,1],[8,-9],[2,-14],[-2,-5],[3,-6],[12,-8],[14,-4],[12,2],[10,-3],[7,-10],[25,-26],[16,-9],[6,-46],[10,-34],[12,-16],[62,-49],[-2,-17],[27,-46],[13,-8],[31,-10],[2,-7],[-2,-8],[5,-18],[16,-13],[11,-5],[39,-2],[10,-10],[24,-3],[3,-20],[-14,-12],[0,-2],[13,-27],[8,-10],[-18,-7],[-5,-14],[6,-14],[10,-11],[18,-15],[20,-10],[50,-14],[65,-5],[71,4],[34,10],[59,-5],[14,1]],[[2874,7006],[1,266]],[[5687,6577],[-22,1],[-13,-2],[-20,-13],[-17,-17],[-4,-15],[0,-10],[11,-6],[9,-9],[-5,-4],[-8,2],[-42,24],[-56,22],[-65,18],[-26,5],[-29,2],[-36,-3],[-27,-12],[-6,-4],[-12,-1],[-46,14],[-15,0],[-15,-6],[-11,-16],[-5,-4],[-18,-2],[-9,6],[-29,-10],[-47,-42],[-10,-14],[-11,-83],[-21,-27],[-7,-45],[4,-11],[-15,-12],[-7,-1],[-33,0],[-7,9],[-18,-3],[-11,-6],[-5,-6],[0,-5],[2,-5],[-1,-5],[-5,-13],[-10,-10],[-19,-6],[-6,1]],[[2874,6505],[-2,0],[-4,-1],[-5,1],[-2,2],[0,1],[2,2],[-2,2],[-17,7],[-6,5],[0,1],[0,1],[-16,6],[-5,0],[-1,-1],[-8,2],[-3,2],[-4,6],[-3,4],[-15,7],[-2,1],[-6,1],[-1,0],[-6,-5],[0,-7],[-9,-2],[-2,1],[-5,3],[-9,3],[-2,0],[-5,-2],[-7,0],[-8,2],[-4,3],[-2,2],[-2,3],[-1,4],[1,3],[0,7],[-4,1],[-1,0],[0,-1],[-6,1],[-2,-1],[-4,-5],[-11,-3],[-18,-4],[-12,-6],[-3,0],[-3,4],[-5,3],[-10,5],[-9,3],[-5,-2],[-10,7],[-2,3],[-6,4],[-56,35],[-7,-2],[1,-3],[-5,-9],[-8,-3],[-5,0],[-5,1],[-9,-2],[-1,-1],[-5,-6],[-2,0],[-5,2],[-3,3],[1,2],[-1,3],[-4,3],[-10,4],[-2,3],[-5,3],[-4,1],[-7,-2],[-2,1],[-5,5],[1,4],[-1,2],[-5,3],[-9,2],[-7,1],[-5,-4],[0,-3],[1,-3],[-2,-3],[-4,-2],[-10,-1],[-7,2],[-6,4],[-1,2],[2,3],[0,1],[-3,3],[-1,0],[-8,20],[0,5],[-1,2],[-3,1],[-6,2],[-11,-1],[-4,2],[-8,1],[-1,-1],[0,-1],[-2,-3],[-5,-5],[-2,-2],[-13,-1],[-5,3],[-13,1],[-7,-3],[-2,-3],[-10,-7],[-10,-3],[-1,1],[-4,9],[-1,4],[0,1],[-6,4],[-4,0],[-3,-2],[-4,-8],[-5,-12],[0,-7],[-2,-12],[-2,-3],[-3,-2],[-9,1],[-13,-1],[-1,0],[0,-4],[-3,0],[-25,6],[-5,0],[-2,0],[-1,0],[-1,1],[1,3],[1,1],[-1,2],[-4,2],[-5,6],[0,2],[1,0],[-1,8],[-4,8],[-6,5],[-5,1],[-11,2],[-8,4],[-8,0],[-7,-3],[-3,-6],[-7,1],[-4,9],[1,5],[-5,4],[-7,3],[-12,1],[-8,-2],[-7,-4],[-2,-1],[-3,-4],[-3,-1],[-2,0],[-5,4],[-1,0],[-2,0],[-1,0],[0,-1],[-1,0],[-1,-1],[-1,-3],[-8,-5],[-5,0],[-2,1],[-3,7],[0,3],[1,2],[6,7],[0,4],[-1,1],[-6,1],[-10,-1],[-5,3],[-6,-6],[6,-5],[0,-3],[0,-2],[-7,1],[-13,-4],[-4,1],[0,1],[-1,2],[-6,3],[-13,6],[-5,1],[-3,-1],[-4,2],[-4,3],[-4,6],[-1,3],[-3,2],[-103,51],[-13,7],[-7,3],[-52,27]],[[7552,4863],[2,-535]],[[6215,4871],[21,33],[3,21],[21,26],[13,29],[22,104],[-4,31],[1,43],[4,14],[14,21],[-1,73],[-7,15],[-5,25],[-5,59],[-7,13],[-1,28]],[[6403,98],[-8,0],[-12,1],[-13,-1],[-15,0],[-25,0],[-36,0],[-60,0],[-7,0],[-104,-1],[-3,1],[-111,-1],[-1,0],[-18,0],[-3,0],[-10,0],[-18,0],[-4,0],[-11,0],[-81,0],[-32,0],[-1,0],[-30,0],[-21,0]],[[4980,3269],[0,33],[-3,23],[-15,52],[-3,44],[-19,81],[-18,33],[-5,10],[-2,4],[-23,32],[-9,16],[-7,24],[0,15],[7,15],[10,12],[67,47],[22,21],[10,14],[1,1],[25,42],[4,7],[13,27]],[[5063,842],[11,17],[43,87],[30,73],[16,56],[0,11],[10,18],[3,9]]],"transform":{"scale":[0.0008005971597159722,0.0006495535553555355],"translate":[-90.418136,41.696089]},"bbox":[-90.418136,41.696089,-82.412965,48.190975]}